[{"categories":["music"],"contents":"這首歌是我第一個學會唱的日語歌，至今在我心中的日語金曲排行榜No.1\n認識這首歌主要是因為鬼滅之刃刀匠村篇片頭曲的關係\n當時雖然不是完整版，但聽完一次過後，只要每播一集，就一定聽完不會跳過\n再搭配上動畫的演出，完完全全給人熱血沸騰的感覺。\n而milet則是因為日劇《秘密內幕～女警的反擊～》主題曲-Ordinary days就被圈粉\n之後於2023年參加她的個人演唱會並達成第一個日本歌手演唱會的成就\n下次再開個主題好好介紹這位歌手與這部日劇\n先讓我們來享受這首歌曲吧!\n另外，底下會提供日文歌詞\n可以一邊聽一邊跟著唱\n最後還會附上歌詞來源，給喜歡聽日語歌學唱日語歌的作為參考喔\n作詞:Jean-Ken Johnny\n作曲:Jean-Ken Johnny\n編曲:MAN WITH A MISSION\n發行日期:2023/05/31\n電視動畫《鬼滅之刃刀匠村篇》片頭曲\n闇夜(やみよ)を駆(か)け抜(ぬ)けて 何処(どこ)へむかう\n月明(つきあ)かりだけがただ一(ひと)つの道標(みちしるべ)\n痛(いた)みも悲(かな)しみも拭(ぬぐ)いきれず\nされどこの胸(むね)の炎(ほのお)は消(け)させない\n誰(た)が為(ため)に僕(ぼく)たちはこの想(おも)いを貫(つらぬ)いて\n闇(やみ)を裂(さ)き陽(ひ)の下(した)で光(ひかり)さす日(ひ)まで\n解(と)き放(はな)たれた心(こころ)に宿(やど)した火(ひ)よ\n舞(ま)い上(あ)げ まとえ 今(いま) 夜明(よあ)けの向(む)こう側(がわ)へ\n君(きみ)がいるこの世界(せかい)もう一度(いちど)愛(あい)せるまで\n我(わ)が命(いのち) 果(は)てようとも 繋(つな)いで行(ゆ)こう\n絆(きずな)が紡(つむ)いで生(う)まれた奇跡(きせき)を\n喜怒哀楽(きどあいらく) 夢(ゆめ) 揺(ゆ)らめいてる現世(うつしよ)\n互(たが)いの正義(せいぎ)をまた繰(く)り返(かえ)し振(ふ)りかざす\n誰(た)が為(ため)に繋(つな)ぐ命(いのち)交(まじ)わりもつれる運命(さだめ)\n蛇(じゃ)の道(みち)数多(あまた)の罪(つみ)全(すべ)て薙(な)ぎ払(はら)え\n解(と)き放(はな)て今(いま) 僕(ぼく)らが起(お)こした火(ひ)を\n舞(ま)い上(あ)げ走(はし)れば明日(あした)が変(か)わるはず\n君(きみ)といるこの世界(せかい)二度(にど)と離(はな)さずに\n君(きみ)と共(とも)に行(ゆ)く\n瞼(まぶた)を閉(と)じても想(おも)い出(だ)すあの日(ひ)を\n打(う)ちのめされても焦(こ)がれた未来(みらい)を\nいつの日(ひ)か君(きみ)に捧(ささ)げてみせよう\n解(と)き放(はな)たれた心(こころ)に宿(やど)した火(ひ)よ\n舞(ま)い上(あ)げ まとえ 今(いま) 夜明(よあ)けの向(む)こうへ\n解(と)き放(はな)て今(いま) 僕(ぼく)らが起(お)こした火(ひ)を\n舞(ま)い上(あ)げ走(はし)れば明日(あした)が変(か)わるはず\n君(きみ)がいたこの世界(せかい)もう一度(いちど)愛(あい)せるまで\n我(わ)が命(いのち) 果(は)てようとも 繋(つな)げていくよ\n絆(きずな)が紡(つむ)いで生(う)まれた奇跡(きせき)を\n歌詞來源\n","permalink":"https://ariesyu0330.github.io/blog/milet/","tags":["詩詞、歌曲","milet","動漫歌曲","鬼滅之刃"],"title":"絆ノ奇跡 - MAN WITH A MISSION × milet"},{"categories":["live"],"contents":"一個人的遠方 獨旅日誌 謝幕之後 觀劇心得 書頁之間 閱讀紀錄 那些被音樂照亮的夜晚 演唱會分享 文藝薰陶 博物館、美術館展覽紀錄 微醺筆記 調酒紀錄 同行的風景 與友人相處時光 字句與旋律之間 詩詞、歌曲分享 尚未抵達的風景 人生100件目標 這裡只是一個喜歡獨自旅行的人\n也喜歡與友人共享日常\n喜歡劇場謝幕後的餘韻\n書頁間的留白\n演唱會裡的燈海\n藝術氣息的氛圍\n以及深夜裡陪伴自己的詩句與旋律\n和些微的酒精溫度\n願多年以後回頭翻閱，仍能記得自己曾如此熱烈生活著。\n","permalink":"https://ariesyu0330.github.io/blog/first/","tags":["獨旅","日劇","書籍","演唱會","展覽","調酒","聚會","詩詞、歌曲","夢想"],"title":"在旅行、書頁、音樂與人際的溫度裡，拾起屬於自己的光"}]